setup.py
ypdd/__init__.py
ypdd/cli.py
ypdd/conf.py
ypdd/core.py
ypdd/version.py
ypdd.egg-info/PKG-INFO
ypdd.egg-info/SOURCES.txt
ypdd.egg-info/dependency_links.txt
ypdd.egg-info/entry_points.txt
ypdd.egg-info/requires.txt
ypdd.egg-info/top_level.txt