Metadata-Version: 1.1
Name: ypdd
Version: 0.0.2
Summary: library for YandexPDD
Home-page: https://github.com/k0st1an/yandex-pdd
Author: Konstantin Kruglov
Author-email: kruglovk@gmail.com
License: Apache License Version 2.0
Platform: UNKNOWN
Classifier: Development Status :: 3 - Alpha
Classifier: License :: OSI Approved :: Apache Software License
Classifier: Programming Language :: Python :: 3 :: Only
Classifier: Operating System :: POSIX :: Linux
